requestlogger/__init__.py
requestlogger/timehacks.py
wsgi_request_logger_bepro-0.4.7.dist-info/LICENSE
wsgi_request_logger_bepro-0.4.7.dist-info/METADATA
wsgi_request_logger_bepro-0.4.7.dist-info/WHEEL
wsgi_request_logger_bepro-0.4.7.dist-info/top_level.txt
wsgi_request_logger_bepro-0.4.7.dist-info/zip-safe
wsgi_request_logger_bepro-0.4.7.dist-info/RECORD
